{
  "category": "Arithmetic",
  "content": "\"\"\"Documentation for Sum up Series\n\n# Sum up Series\n\n## Description\nThis component sums up a Pandas Series.\n\n## Inputs\n* **data** (Pandas Series): The values must be numeric.\n\n## Outputs\n* **sum** (Float): The sum of alls values of data.\n\n## Details\nThis component calculates the sum of the provided series.\n\n## Examples \nThe json input of a typical call of this component with a Pandas Series is\n```\n{\n\t\"data\": {\n\t\t\t\t\"2019-08-01T15:20:12\": 0,\n\t\t\t\t\"2019-08-01T15:44:12\": 3,\n\t\t\t\t\"2019-08-03T16:20:15\": null  \n\t}\n}\n```\nThe expected output is\n```\n\t\"sum\": 4\n\n```\n\"\"\"\n\n# ***** DO NOT EDIT LINES BELOW *****\n# These lines may be overwritten if component details or inputs/outputs change.\nCOMPONENT_INFO = {\n    \"inputs\": {\n        \"data\": {\"data_type\": \"SERIES\"},\n    },\n    \"outputs\": {\n        \"sum\": {\"data_type\": \"FLOAT\"},\n    },\n    \"name\": \"Sum up Series\",\n    \"category\": \"Arithmetic\",\n    \"description\": \"Calculates the sum of a Series\",\n    \"version_tag\": \"1.0.0\",\n    \"id\": \"878d85a2-2cf5-235b-d260-fd94c734cec9\",\n    \"revision_group_id\": \"878d85a2-2cf5-235b-d260-fd94c734cec9\",\n    \"state\": \"RELEASED\",\n    \"released_timestamp\": \"2022-02-09T17:33:31.783721+00:00\",\n}\n\nfrom hdutils import parse_default_value  # noqa: E402, F401\n\n\ndef main(*, data):\n    # entrypoint function for this component\n    # ***** DO NOT EDIT LINES ABOVE *****\n    # write your function code here.\n\n    return {\"sum\": data.sum()}\n\n\nTEST_WIRING_FROM_PY_FILE_IMPORT = {}\nRELEASE_WIRING = {}\n",
  "description": "Calculates the sum of a Series",
  "documentation": "# Sum up Series\n\n## Description\nThis component sums up a Pandas Series.\n\n## Inputs\n* **data** (Pandas Series): The values must be numeric.\n\n## Outputs\n* **sum** (Float): The sum of alls values of data.\n\n## Details\nThis component calculates the sum of the provided series.\n\n## Examples \nThe json input of a typical call of this component with a Pandas Series is\n```\n{\n\t\"data\": {\n\t\t\t\t\"2019-08-01T15:20:12\": 0,\n\t\t\t\t\"2019-08-01T15:44:12\": 3,\n\t\t\t\t\"2019-08-03T16:20:15\": null  \n\t}\n}\n```\nThe expected output is\n```\n\t\"sum\": 4\n\n```\n",
  "id": "878d85a2-2cf5-235b-d260-fd94c734cec9",
  "io_interface": {
    "inputs": [
      {
        "data_type": "SERIES",
        "id": "2bf8a46c-95bb-2364-6cb0-fe45e12fdf0c",
        "name": "data",
        "type": "REQUIRED"
      }
    ],
    "outputs": [
      {
        "data_type": "FLOAT",
        "id": "03643e0b-1fe7-a9a9-5c1b-e9452265a40a",
        "name": "sum"
      }
    ]
  },
  "name": "Sum up Series",
  "release_wiring": {
    "dashboard_positionings": [],
    "input_wirings": [],
    "output_wirings": []
  },
  "released_timestamp": "2022-02-09T17:33:31.783721+00:00",
  "revision_group_id": "878d85a2-2cf5-235b-d260-fd94c734cec9",
  "state": "RELEASED",
  "test_wiring": {
    "dashboard_positionings": [],
    "input_wirings": [],
    "output_wirings": []
  },
  "type": "COMPONENT",
  "version_tag": "1.0.0"
}